rasm_arch/__init__.py
rasm_arch/rasm_arch.py
rasm_arch/util.py
rasm_arch-1.2.5.data/scripts/rasm-arch
rasm_arch_data/__init__.py
rasm_arch_data/mushaf_simple.json
rasm_arch_data/mushaf_uthmani.json
rasm_arch-1.2.5.dist-info/LICENSE
rasm_arch-1.2.5.dist-info/METADATA
rasm_arch-1.2.5.dist-info/WHEEL
rasm_arch-1.2.5.dist-info/top_level.txt
rasm_arch-1.2.5.dist-info/RECORD
