Metadata-Version: 2.1
Name: rasm-arch
Version: 1.2.5
Summary: text utility for converting Arabic-scripted text to a completely dediacritised skeleton
Home-page: https://github.com/kabikaj/rasm_arch
Download-URL: https://github.com/kabikaj/rasm_arch
Author: Alicia González Martínez and Thomas Milo
Author-email: aliciagm85+kabikaj@gmail.com
License: MIT
Keywords: arabic,persian,urdu,quran,manuscript,rasm,unicode,NLP,digital humanities
Classifier: Development Status :: 5 - Production/Stable
Classifier: Intended Audience :: Developers
Classifier: Intended Audience :: Information Technology
Classifier: License :: OSI Approved :: MIT License
Classifier: Natural Language :: Arabic
Classifier: Natural Language :: Persian
Classifier: Natural Language :: Urdu
Classifier: Operating System :: OS Independent
Classifier: Programming Language :: Python :: 3.8
Classifier: Topic :: Religion
Classifier: Topic :: Scientific/Engineering :: Information Analysis
Classifier: Topic :: Text Processing :: Linguistic
License-File: LICENSE
